dooo/__init__.py
dooo/code_execution.py
dooo/core.py
dooo/llm_utils.py
dooo/prompts.py
dooo-0.1.5.dist-info/LICENSE
dooo-0.1.5.dist-info/METADATA
dooo-0.1.5.dist-info/WHEEL
dooo-0.1.5.dist-info/top_level.txt
dooo-0.1.5.dist-info/RECORD
