Metadata-Version: 2.1
Name: dooo
Version: 0.1.5
Summary: A Python package to make LLMs easy
Home-page: https://github.com/andrewgcodes/dooo
Author: Andrew Gao and William Gao
Author-email: olafblitz@gmail.com
Classifier: Programming Language :: Python :: 3
Classifier: License :: OSI Approved :: MIT License
Classifier: Operating System :: OS Independent
Requires-Python: >=3.6
License-File: LICENSE
Requires-Dist: litellm
Requires-Dist: numpy
Requires-Dist: pandas
Requires-Dist: matplotlib
Requires-Dist: scipy
Requires-Dist: requests
